
{
    "logo": "AmCbunq",
    "homePage": {
        "slogan": "Su banco de crédito mutuo",
        "nav": {
            "home": "Inicio",
            "features": "Características",
            "pricing": "Precios",
            "help": "Ayuda",
            "openAccount": "Abrir una cuenta",
            "login": "Iniciar sesión"
        },
        "hero": {
            "title_part1": "Banca, simplificada e ",
            "title_highlight": "inteligente.",
            "subtitle": "Gestione sus finanzas con potentes herramientas, transacciones instantáneas y seguridad de primer nivel.",
            "ctaPrimary": "Comience hoy",
            "ctaSecondary": "Saber más"
        },
        "featuresSection": {
            "title": "Una experiencia bancaria diseñada para usted",
            "feature1": {
                "title": "Gestione su presupuesto sin esfuerzo",
                "description": "Con la app AmCbunq, simplifique la gestión diaria de su presupuesto. ¡Abra una cuenta, obtenga una tarjeta, siga sus gastos y gestione su presupuesto en una sola aplicación!",
                "cta": "Descubrir la aplicación"
            },
            "feature2": {
                "title": "Tarjetas que se adaptan a usted",
                "description": "Física o virtual, elija la tarjeta que más le convenga. Disfrute de pagos seguros y límites personalizables para controlar sus gastos.",
                "cta": "Explorar tarjetas"
            },
            "feature3": {
                "title": "IA a su servicio",
                "description": "Nuestro asistente de IA analiza sus gastos para ofrecerle consejos personalizados y ayudarle a identificar oportunidades de ahorro. Tome el control de sus finanzas.",
                "cta": "Ver funciones de IA"
            }
        },
        "pricingSection": {
            "title": "Ofertas claras para todas sus necesidades",
            "account": {
                "title": "Cuenta y Tarjeta AmCbunq",
                "description": "La cuenta diaria para seguir sus gastos y simplificar la gestión de su presupuesto.",
                "features": [
                    "Pague sus facturas con tarjeta",
                    "Gestione su presupuesto",
                    "Tarjeta Visa Internacional",
                    "Tarjetas virtuales para compras en línea",
                    "Depósitos y retiros de efectivo en puntos de venta",
                    "Cashback automático en sus compras"
                ],
                "price": "2,99 €/mes",
                "cta": "Abrir una cuenta"
            },
            "bills": {
                "title": "Facturas AmCbunq",
                "description": "Controle su presupuesto, decida cuándo y cómo pagar sus gastos con nuestros servicios.",
                "features": [
                    "Pago de facturas en efectivo",
                    "Pago de sus facturas con tarjeta"
                ],
                "price": "Gratis",
                "cta": "Descargar la aplicación"
            }
        },
        "partnersSection": {
            "title": "Nuestros Socios",
            "invitation": "¿Es usted un gran emisor de facturas y desea ofrecer los servicios de AmCbunq a sus clientes?",
            "description": "Hágase socio de AmCbunq y ofrezca a sus usuarios soluciones de pago en efectivo o con tarjeta en uno de los 10.000 puntos de pago autorizados."
        },
        "footer": {
            "legal": "Aviso Legal",
            "copyright": "© 2024 AmCbunq. Todos los derechos reservados."
        },
        "animatedFeatures": {
            "mainAccount": "Cuenta Principal",
            "savings": "Ahorro Express",
            "stocks": "Acciones y ETF",
            "crypto": "Cripto"
        }
    },
    "login": {
      "title": "Iniciar sesión",
      "description": "Ingrese sus credenciales para acceder a su cuenta.",
      "emailLabel": "Correo electrónico",
      "emailPlaceholder": "nombre@ejemplo.com",
      "passwordLabel": "Contraseña",
      "forgotPassword": "¿Olvidó su contraseña?",
      "loginButton": "Iniciar sesión",
      "registerPrompt": "¿No tiene una cuenta?",
      "registerLink": "Regístrese",
      "backToHome": "Volver al inicio",
      "loginErrorTitle": "Error de inicio de sesión",
      "verifyEmailError": "Por favor, verifique su correo electrónico antes de iniciar sesión."
    },
    "register": {
      "title": "Abrir una cuenta en AmCbunq",
      "description": "Regístrese para comenzar a administrar sus finanzas.",
      "firstNameLabel": "Nombre",
      "firstNamePlaceholder": "Juan",
      "lastNameLabel": "Apellido",
      "lastNamePlaceholder": "Pérez",
      "phoneLabel": "Número de teléfono",
      "cityLabel": "Ciudad",
      "postalCodeLabel": "Código Postal",
      "confirmPasswordLabel": "Confirmar contraseña",
      "termsPrompt": "Al crear una cuenta, usted acepta nuestros",
      "termsLink": "Términos y Condiciones",
      "createAccountButton": "Abrir mi cuenta",
      "loginPrompt": "¿Ya tiene una cuenta?",
      "loginLink": "Iniciar sesión",
      "dobLabel": "Fecha de nacimiento",
      "pobLabel": "Lugar de nacimiento",
      "nationalityLabel": "Nacionalidad",
      "residenceCountryLabel": "País de residencia",
      "addressLabel": "Dirección de residencia",
      "professionLabel": "Profesión",
      "salaryLabel": "Ingresos mensuales (aprox. en €)",
      "dobPlaceholder": "Seleccione una fecha",
      "registerErrorTitle": "Error de registro",
      "registerErrorDescription": "Ocurrió un error inesperado durante el registro.",
      "emailInUseError": "Esta dirección de correo electrónico ya está en uso por otra cuenta.",
      "permissionDeniedError": "Permisos faltantes o insuficientes. Por favor, revise sus reglas de seguridad de Firestore."
    },
     "verifyEmail": {
        "title": "Verifique su dirección de correo electrónico",
        "description": "Hemos enviado un enlace de verificación a {email}. Por favor, haga clic en el enlace para activar su cuenta.",
        "resendButton": "Reenviar correo electrónico",
        "backToLogin": "Volver a iniciar sesión",
        "emailSent": "¡Correo electrónico enviado!",
        "emailSentDescription": "Se ha enviado un nuevo correo electrónico de verificación a su dirección.",
        "checkSpam": "Recuerde también revisar su carpeta de correo no deseado (spam).",
        "verificationSuccessTitle": "¡Correo electrónico verificado!",
        "verificationSuccessDescription": "Su dirección de correo electrónico ha sido verificada con éxito. Por favor, inicie sesión con sus nuevas credenciales para disfrutar de su experiencia bancaria.",
        "proceedToLoginButton": "Proceder a iniciar sesión",
        "verifyingTitle": "Verificando su correo electrónico...",
        "verifyingDescription": "Por favor, espere un momento.",
        "verificationErrorTitle": "Error de verificación",
        "invalidAction": "La acción solicitada no es válida.",
        "expiredLinkError": "El enlace de verificación no es válido o ha caducado. Por favor, solicite un nuevo enlace."
    },
    "sidebar": {
      "dashboard": "Panel",
      "accounts": "Cuentas",
      "iban": "Mi IBAN",
      "transfers": "Transferencias",
      "cards": "Tarjetas",
      "history": "Historial",
      "budgets": "Presupuestos",
      "settings": "Configuración",
      "more": "Más",
      "help": "Ayuda y Soporte",
      "documents": "Mis Documentos",
      "exchange": "Cambio de Divisas",
      "referrals": "Recomendar a un Amigo",
      "notifications": "Notificaciones",
      "verified": "Verificado",
      "unverified": "No verificado",
      "userMenu": {
        "profile": "Perfil",
        "billing": "Facturación",
        "settings": "Configuración",
        "logout": "Cerrar sesión"
      }
    },
    "sidebarGroups": {
        "account": "Mi Cuenta",
        "settingsAndMore": "Configuración y Más"
    },
    "dashboard": {
      "title": "Panel",
      "totalBalance": "Saldo Total",
      "greeting": "Hola",
      "accountSummary": "Resumen de cuenta",
      "checkingAccount": "Cuenta Corriente",
      "savingsAccount": "Cuenta de Ahorros",
      "creditCard": "Tarjeta de Crédito",
      "recentTransactions": "Transacciones Recientes",
      "transaction": {
        "description": "Descripción",
        "category": "Categoría",
        "date": "Fecha",
        "amount": "Monto"
      },
      "expenseChart": "Resumen de Gastos",
      "noExpenseData": "No hay datos de gastos para mostrar.",
      "aiAssistant": {
        "title": "Asistente Financiero de IA",
        "description": "Obtenga información y recomendaciones personalizadas basadas en su historial de transacciones.",
        "button": "Obtener Información de IA",
        "loading": "Analizando sus finanzas...",
        "insightsTitle": "Sus Perspectivas Financieras",
        "overspendingAlert": "¡Alerta de Gasto Excesivo!",
        "savingsAlert": "¡Oportunidad de Ahorro!",
        "noInsights": "No se pudieron generar perspectivas en este momento."
      },
      "quickActions": {
        "title": "Acciones Rápidas",
        "makeTransfer": "Hacer una Transferencia",
        "payBill": "Pagar una Factura",
        "addBeneficiary": "Añadir Beneficiario",
        "viewHistory": "Ver Historial",
        "settings": "Configuración"
      },
      "ourServicesTitle": "Nuestros Servicios",
      "ourServicesDescription": "Descubra nuestra gama de servicios diseñados para ayudarle a hacer crecer su patrimonio.",
      "carbonFootprintTitle": "Su Huella de Carbono",
      "carbonFootprintDescription": "Siga el impacto ambiental de sus gastos y contribuya a un planeta más verde.",
      "verificationBanner": {
        "title": "Verificación Pendiente",
        "description": "Complete su verificación de identidad",
        "button": "Verificar ahora",
        "pending_title": "Verificación en Proceso",
        "pending_description": "Sus documentos están siendo revisados. Esto generalmente toma de 24 a 48 horas."
      },
       "notifications": {
        "title": "Notificaciones",
        "welcomeTitle": "¡Bienvenido a AmCbunq!",
        "welcomeDescription": "Su cuenta ha sido creada con éxito. Ahora puede explorar todas las funciones que ofrecemos. Asegúrese de completar la verificación de su perfil lo antes posible para desbloquear todas las funcionalidades.",
        "verificationTitle": "Verificación de perfil",
        "verificationDescription": "Por favor, complete su verificación de identidad. Para cumplir con las regulaciones financieras y garantizar la seguridad de su cuenta, este es un paso necesario para acceder a funciones como transferencias y servicios de tarjeta.",
        "viewAll": "Ver todas las notificaciones",
        "noNotifications": "No hay nuevas notificaciones.",
        "markAllAsRead": "Marcar todo como leído"
      }
    },
    "accounts": {
      "title": "Mis Cuentas",
      "totalBalance": "Saldo Total",
      "totalBalanceDescription": "Activos totales en todas sus cuentas.",
      "addAccount": "Añadir Cuenta",
      "details": "Ver Detalles",
      "checking": "Cuenta Corriente",
      "savings": "Cuenta de Ahorros",
      "credit": "Tarjeta de Crédito",
      "internalTransferTitle": "Transferencia Interna",
      "internalTransferDescription": "Mueva fondos entre sus cuentas al instante.",
      "fromAccount": "Desde la cuenta",
      "toAccount": "A la cuenta",
      "transferAmount": "Monto",
      "submitTransfer": "Enviar Transferencia",
      "accountingTitle": "Libro de Cuentas",
      "creditLedger": "Crédito",
      "debitLedger": "Débito",
      "balanceLedger": "Saldo",
      "accountNumber": "Número de Cuenta",
      "accountDetailsDescription": "Transacciones recientes para esta cuenta."
    },
    "transfers": {
      "title": "Hacer una Transferencia",
      "newTransfer": "Nueva Transferencia",
      "newTransferDescription": "Envíe dinero a cualquier cuenta bancaria.",
      "from": "Desde",
      "selectAccount": "Seleccione una cuenta",
      "to": "Para",
      "selectBeneficiary": "Seleccione un beneficiario",
      "amount": "Monto",
      "description": "Descripción (opcional)",
      "descriptionPlaceholder": "p. ej., pago de alquiler",
      "submit": "Enviar Transferencia",
      "recentTransfers": "Transferencias Recientes",
      "addBeneficiary": "Añadir Beneficiario",
      "noRecentTransfers": "No se encontraron transferencias recientes.",
      "addBeneficiaryTitle": "Añadir un nuevo beneficiario",
      "addBeneficiaryDescription": "Introduzca los datos del nuevo beneficiario. Se guardarán para futuras transferencias.",
      "beneficiaryNameLabel": "Nombre del beneficiario",
      "beneficiaryNamePlaceholder": "Juan Pérez",
      "beneficiaryIbanLabel": "IBAN",
      "beneficiaryBicLabel": "BIC / SWIFT",
      "beneficiaryNicknameLabel": "Apodo (opcional)",
      "beneficiaryNicknamePlaceholder": "ej: Propietario",
      "saveBeneficiaryButton": "Guardar beneficiario",
      "beneficiaryAdded": "¡Beneficiario añadido!",
      "beneficiaryAddedDescription": "ha sido añadido correctamente a su lista de beneficiarios.",
      "cancelButton": "Cancelar",
      "unverified_title": "Hacer una Transferencia",
      "unverified_description": "Complete su verificación de identidad para enviar y recibir dinero."
    },
    "cards": {
      "title": "Mis Tarjetas",
      "orderCard": "Pedir una Nueva Tarjeta",
      "cardBankName": "Banco AmCbunq",
      "cardHolder": "Titular de la Tarjeta",
      "validThru": "Válida hasta",
      "settings": "Configuración de la Tarjeta",
      "settingsDescription": "Gestione la configuración y seguridad de su tarjeta.",
      "freeze": "Bloquear Tarjeta",
      "freezeDescription": "Bloquee temporalmente su tarjeta.",
      "setLimit": "Establecer Límites de Gasto",
      "setLimitDescription": "Controle sus gastos mensuales.",
      "viewPin": "Ver PIN",
      "viewPinDescription": "Vea el PIN de su tarjeta de forma segura.",
      "orderCardTitle": "Pedir una nueva tarjeta física",
      "orderCardDescription": "Está a punto de pedir una tarjeta. Esto es gratuito. La tarjeta se enviará a su dirección residencial registrada.",
      "request_card_confirm_title": "Confirmar solicitud de tarjeta",
      "request_card_confirm_description": "¿Confirma que desea solicitar una nueva tarjeta física? Se enviará a su dirección registrada.",
      "confirmOrder": "Confirmar Pedido",
      "cancelButton": "Cancelar",
      "cardOrdered": "¡Tarjeta Pedida!",
      "cardOrderedDescription": "Su nueva tarjeta está en camino.",
      "card_request_success": "¡Solicitud de tarjeta enviada!",
      "cardFrozen": "La tarjeta ha sido bloqueada.",
      "cardUnfrozen": "La tarjeta ha sido desbloqueada.",
      "limitUpdated": "Límite de gasto actualizado.",
      "setLimitTitle": "Establecer Límite de Gasto",
      "setLimitDescription": "Introduzca un nuevo límite de gasto mensual para su tarjeta.",
      "currentLimit": "Límite Actual",
      "newLimitLabel": "Nuevo Límite Mensual",
      "saveButton": "Guardar Límite",
      "viewPinTitle": "PIN de su Tarjeta",
      "viewPinDescription": "Por su seguridad, este PIN se mostrará por un tiempo limitado.",
      "yourPinIs": "Su PIN es:",
      "closeButton": "Cerrar",
      "showPin": "Mostrar PIN",
      "hidePin": "Ocultar PIN",
      "unverified_title": "Administre sus Tarjetas",
      "unverified_description": "Complete su verificación de identidad para pedir nuevas tarjetas y administrar la configuración de su tarjeta.",
      "request_pending_title": "Solicitud de tarjeta en curso",
      "request_pending_description": "Hemos recibido su solicitud de tarjeta. Se está procesando y se le notificará cuando se envíe.",
      "cardActive": "Tarjeta Activa"
    },
    "history": {
      "title": "Historial de Transacciones",
      "filters": "Filtros",
      "dateRange": "Seleccione un rango de fechas",
      "transactionType": "Tipo de Transacción",
      "all": "Todos",
      "income": "Ingresos",
      "expense": "Gastos",
      "applyFilters": "Aplicar Filtros",
      "noTransactions": "No se encontraron transacciones para el período seleccionado.",
      "table": {
        "date": "Fecha",
        "description": "Descripción",
        "category": "Categoría",
        "status": "Estado",
        "amount": "Monto",
        "statuses": {
          "completed": "Completado",
          "pending": "Pendiente",
          "failed": "Fallido"
        }
      }
    },
    "budgets": {
      "title": "Mis Presupuestos",
      "createBudget": "Crear Presupuesto",
      "spentOf": "Gastado {spent} de {total}",
      "groceries": "Comestibles",
      "transport": "Transporte",
      "entertainment": "Entretenimiento",
      "createBudgetTitle": "Crear un Nuevo Presupuesto",
      "createBudgetDescription": "Establezca un nombre y un monto mensual para su nueva categoría de presupuesto.",
      "budgetNameLabel": "Nombre del Presupuesto",
      "budgetNamePlaceholder": "p. ej., Cafeterías",
      "budgetAmountLabel": "Monto Total",
      "saveBudgetButton": "Crear Presupuesto",
      "budgetCreated": "¡Presupuesto Creado!",
      "budgetCreatedDescription": "Su nuevo presupuesto '{name}' ha sido creado.",
      "noBudgetsTitle": "Aún no tiene presupuestos",
      "noBudgetsDescription": "Cree un presupuesto para comenzar a controlar sus gastos y alcanzar sus metas financieras."
    },
    "documents": {
      "title": "Mis Documentos",
      "description": "Administre sus documentos cargados.",
      "upload": "Subir Documento",
      "documentName": "Nombre del Documento",
      "uploadDate": "Fecha de Carga",
      "download": "Descargar",
      "actions": "Acciones",
      "serviceContract": "Acuerdo de Servicio.pdf",
      "privacyPolicy": "Política de Privacidad.pdf"
    },
    "iban": {
      "title": "Mis Datos de IBAN",
      "description": "Use estos datos para recibir dinero de otras cuentas.",
      "accountDetails": "Detalles de la Cuenta",
      "accountHolder": "Titular de la Cuenta",
      "iban": "IBAN",
      "bic": "BIC / SWIFT",
      "copy": "Copiar",
      "copied": "¡Copiado!",
      "copiedDescription": "ha sido copiado a su portapapeles.",
      "downloadIban": "Descargar IBAN",
      "clientAddress": "Dirección del cliente",
      "unverified_title": "Acceda a su IBAN",
      "unverified_description": "Complete su verificación de identidad para ver y usar sus datos de IBAN para recibir pagos.",
      "pending_title": "¡Su cuenta está validada!",
      "pending_description": "Su IBAN se está generando y estará disponible en esta página dentro de las 24 horas hábiles.",
      "pending_button": "Volver al Panel"
    },
    "more": {
      "title": "Más Opciones",
      "help": "Ayuda y Soporte",
      "documents": "Mis Documentos",
      "exchange": "Cambio de Divisas",
      "referrals": "Recomendar a un Amigo"
    },
    "settings": {
      "title": "Configuración",
      "tabs": {
        "profile": "Perfil",
        "security": "Seguridad",
        "notifications": "Notificaciones",
        "appearance": "Apariencia"
      },
      "profile": {
        "title": "Información Personal",
        "description": "Actualice sus datos personales aquí. Esta información es necesaria para la verificación de la cuenta.",
        "nameLabel": "Nombre completo",
        "firstNameLabel": "Nombre",
        "lastNameLabel": "Apellido",
        "emailLabel": "Dirección de correo electrónico",
        "phoneLabel": "Número de teléfono",
        "dobLabel": "Fecha de nacimiento",
        "dobPlaceholder": "Seleccione una fecha",
        "addressGroupTitle": "Dirección Postal",
        "streetLabel": "Dirección",
        "cityLabel": "Ciudad",
        "postalCodeLabel": "Código Postal",
        "countryLabel": "País",
        "saveButton": "Guardar cambios",
        "updateError": "Error al actualizar el perfil",
        "saveSuccess": "¡Perfil actualizado con éxito!"
      },
      "security": {
        "title": "Seguridad",
        "description": "Actualice su contraseña y gestione la seguridad de su cuenta.",
        "currentPasswordLabel": "Contraseña actual",
        "newPasswordLabel": "Nueva contraseña",
        "confirmPasswordLabel": "Confirmar nueva contraseña",
        "saveButton": "Actualizar contraseña",
        "passwordUpdateSuccess": "¡Contraseña actualizada con éxito!",
        "passwordUpdateErrorTitle": "Error de Actualización",
        "passwordUpdateError": "Ocurrió un error.",
        "reauthenticationRequired": "Esta es una operación sensible y requiere autenticación reciente. Por favor, inicie sesión de nuevo antes de volver a intentarlo.",
        "passwordLengthError": "La contraseña debe tener al menos 6 caracteres.",
        "passwordMismatchError": "Las contraseñas no coinciden."
      },
      "notifications": {
        "title": "Notificaciones",
        "description": "Configure cómo recibe las notificaciones.",
        "email": {
          "title": "Notificaciones por correo electrónico",
          "description": "Reciba correos electrónicos sobre la actividad de su cuenta."
        },
        "promotions": {
          "title": "Correos de marketing",
          "description": "Reciba correos electrónicos sobre nuevos productos, funciones y promociones."
        },
        "security": {
          "title": "Alertas de seguridad",
          "description": "Reciba correos electrónicos sobre alertas de seguridad en su cuenta."
        },
        "saveButton": "Guardar preferencias",
        "saveSuccess": "¡Preferencias guardadas!"
      },
      "appearance": {
        "title": "Apariencia",
        "description": "Personalice el aspecto de su panel.",
        "theme": "Tema",
        "themeLight": "Claro",
        "themeDark": "Oscuro",
        "themeSystem": "Sistema",
        "language": "Idioma",
        "languageEn": "Inglés",
        "languageFr": "Francés",
        "languageDe": "Alemán",
        "languageEs": "Español",
        "languagePt": "Portugués",
        "saveButton": "Guardar Cambios"
      }
    },
    "help": {
      "title": "Ayuda y Soporte",
      "faqTitle": "Preguntas Frecuentes",
      "faqDescription": "Encuentre respuestas a las preguntas más frecuentes.",
      "contactTitle": "Contacto",
      "contactDescription": "¿No encuentra lo que busca? Póngase en contacto con nuestro equipo de soporte.",
      "faq": [
        { "question": "¿Cómo abro una cuenta?", "answer": "Puede abrir una cuenta directamente desde nuestra página de inicio haciendo clic en 'Abrir una cuenta'. El proceso es rápido y solo toma unos minutos." },
        { "question": "¿Qué documentos necesito para la verificación?", "answer": "Para la verificación, necesitará un documento de identidad con foto válido emitido por el gobierno (Pasaporte o DNI), un comprobante de domicilio (como una factura de servicios públicos), y deberá tomarse una selfie para la verificación biométrica." },
        { "question": "¿Qué tan seguro está mi dinero?", "answer": "Su seguridad es nuestra máxima prioridad. Usamos encriptación de última generación, autenticación de dos factores y cumplimos con estrictos estándares regulatorios para proteger su dinero y sus datos." },
        { "question": "¿Hay alguna tarifa?", "answer": "Creemos en la transparencia de precios. Puede encontrar nuestra estructura de tarifas en nuestra página de precios. Muchos servicios estándar como el mantenimiento de la cuenta son gratuitos." }
      ],
      "contactForm": {
        "nameLabel": "Nombre",
        "namePlaceholder": "Su nombre",
        "nameRequired": "El nombre es obligatorio.",
        "emailLabel": "Correo electrónico",
        "emailPlaceholder": "Su correo electrónico",
        "emailInvalid": "Dirección de correo electrónico no válida.",
        "subjectLabel": "Asunto",
        "subjectPlaceholder": "¿En qué podemos ayudarle?",
        "subjectRequired": "El asunto es obligatorio.",
        "messageLabel": "Mensaje",
        "messagePlaceholder": "Describa su problema aquí...",
        "messageRequired": "El mensaje es obligatorio.",
        "submitButton": "Enviar mensaje",
        "successTitle": "¡Mensaje enviado!",
        "successDescription": "Gracias por contactarnos. Nos pondremos en contacto con usted lo antes posible.",
        "errorDescription": "No se pudo enviar el mensaje. Por favor, inténtelo de nuevo más tarde."
      }
    },
    "kyc": {
      "title": "Verificación de Identidad",
      "progress": "Paso {step} de {totalSteps}",
      "step1_title": "Vamos a verificar su identidad",
      "step1_desc": "Para proteger su cuenta y cumplir con las regulaciones, necesitamos verificar su identidad. Este proceso es rápido y seguro.",
      "step1_item1": "Un documento de identidad con foto válido emitido por el gobierno (Pasaporte, DNI).",
      "step1_item2": "Una foto reciente de usted (selfie) para subir.",
      "step1_item3": "Un comprobante de domicilio reciente (factura de servicios públicos, extracto bancario).",
      "step1_button": "Iniciar Verificación",
      "step2_title": "Cargue su documento",
      "step2_desc": "Por favor, elija el tipo de documento que desea usar y cargue una foto clara del mismo.",
      "step2_doc_type": "Tipo de Documento",
      "step2_doc_passport": "Pasaporte",
      "step2_doc_id": "Documento de Identidad",
      "step3_title_id": "Cargue su Documento de Identidad",
      "step3_title_passport": "Cargue su Pasaporte",
      "step3_desc": "Por favor, cargue una imagen clara y legible del documento completo.",
      "step3_upload_button": "Elegir un archivo",
      "step4_title": "Cargue su comprobante de domicilio",
      "step4_desc": "Cargue una factura de servicios públicos reciente (menos de 3 meses) o un extracto bancario que muestre su nombre y dirección.",
      "step5_title": "Verificación por Selfie",
      "step5_desc": "Tome una foto de usted para confirmar su identidad. Asegúrese de que su rostro esté bien iluminado y sea completamente visible.",
      "step6_title": "Verificación Enviada",
      "step6_desc": "Gracias por enviar sus documentos. Ahora estamos revisando su información. El tiempo de procesamiento suele ser de 24 a 48 horas. Le notificaremos una vez que el proceso esté completo.",
      "step6_button": "Volver al Panel",
      "button_next": "Siguiente",
      "button_back": "Atrás",
      "button_submit": "Enviar Verificación",
      "unverified_title": "Se Requiere Verificación de Identidad",
      "unverified_description": "Para acceder a esta función, primero debe completar su verificación de identidad. Es un proceso rápido y seguro para proteger su cuenta.",
      "unverified_button": "Verificar Mi Identidad",
      "unverified_budgets_title": "Administre sus Presupuestos",
      "unverified_cards_title": "Administre sus Tarjetas",
      "pending_title": "Verificación en Proceso",
      "pending_description": "Sus documentos están siendo revisados. Esto suele tardar entre 24 y 48 horas. Puede seguir navegando por su panel.",
      "selected": "seleccionado",
      "clickNext": "Haga clic en 'Siguiente' para continuar.",
      "readyToProceed": "¿Listo para proceder?",
      "clickSubmit": "Haga clic en 'Enviar' para finalizar su solicitud de verificación.",
      "file_selected": "Archivo seleccionado: {fileName}",
      "file_too_large": "Archivo demasiado grande",
      "file_too_large_desc": "Por favor, seleccione un archivo de menos de 5MB.",
      "missing_documents": "Documentos faltantes",
      "missing_documents_desc": "Por favor, cargue todos los documentos requeridos antes de enviar.",
      "submission_error": "Error de envío",
      "submission_error_desc": "No se pudieron enviar sus documentos. Por favor, inténtelo de nuevo."
    },
    "notFound": {
      "title": "¡Vaya! Página no encontrada.",
      "description": "La página que busca podría haber sido eliminada, haber cambiado de nombre o no estar disponible temporalmente.",
      "button": "Ir a la Página de Inicio"
    }
}
